CheKiPEUQ/CiteSoftLocal.py
CheKiPEUQ/CombinationGeneratorModule.py
CheKiPEUQ/InverseProblem.py
CheKiPEUQ/LICENSE.txt
CheKiPEUQ/MANUAL.txt
CheKiPEUQ/UserInput.py
CheKiPEUQ/__init__.py
CheKiPEUQ/mumpce_custom_plotting_example.py
CheKiPEUQ/nestedObjectsFunctionsLocal.py
CheKiPEUQ/parallel_processing.py
CheKiPEUQ/plotting_functions.py
CheKiPEUQ/test_pytest.py
CheKiPEUQ/mumpce/Project.py
CheKiPEUQ/mumpce/__init__.py
CheKiPEUQ/mumpce/measurement.py
CheKiPEUQ/mumpce/model.py
CheKiPEUQ/mumpce/response_surface.py
CheKiPEUQ/mumpce/solution.py
CheKiPEUQ/simulationDriver/__init__.py
CheKiPEUQ/simulationDriver/canteraKineticsParametersParser.py
CheKiPEUQ/simulationDriver/canteraSimulate.py
CheKiPEUQ/simulationDriver/ceO2_input_simulation_settings.py
CheKiPEUQ/simulationDriver/example_modifyAllAdjustableReactionParametersArrayValues.py
CheKiPEUQ/simulationDriver/example_runfile.py
CheKiPEUQ-0.9.8.data/data/LICENSE.txt
CheKiPEUQ-0.9.8.data/data/MANUAL.txt
CheKiPEUQ-0.9.8.dist-info/METADATA
CheKiPEUQ-0.9.8.dist-info/WHEEL
CheKiPEUQ-0.9.8.dist-info/top_level.txt
CheKiPEUQ-0.9.8.dist-info/RECORD
