Metadata-Version: 2.1
Name: CheKiPEUQ
Version: 0.9.8
Summary: This is the CheKiPEUQ package which stands for Chemical Kinetics Parameter Estimation and Uncertainty Quantification. See https://github.com/AdityaSavara/CheKiPEUQ for more information.
Home-page: https://github.com/AdityaSavara/CheKiPEUQ
Author: Aditya Savara
Author-email: AditySavara2008@u.northwestern.edu
License: BSD-3-Clause
Platform: UNKNOWN
Classifier: License :: OSI Approved :: BSD License
Classifier: Programming Language :: Python
Classifier: Programming Language :: Python :: 3
Classifier: Programming Language :: Python :: 3.6
Classifier: Programming Language :: Python :: Implementation :: CPython
Classifier: Programming Language :: Python :: Implementation :: PyPy
Requires-Python: >=3.5.0
Provides-Extra: complete
Requires-Dist: UnitTesterSG (>=5.4.1) ; extra == 'complete'
Requires-Dist: matplotlib ; extra == 'complete'
Requires-Dist: scipy ; extra == 'complete'
Requires-Dist: numpy ; extra == 'complete'
Requires-Dist: pandas ; extra == 'complete'
Requires-Dist: CiteSoft ; extra == 'complete'
Requires-Dist: zeus-mcmc ; extra == 'complete'
Requires-Dist: dill ; extra == 'complete'
